Workbook

Sheet START
A1: 💍 Unser Hochzeitsplaner
A2: Alle gelb hinterlegten Felder ausfüllen — alles andere rechnet sich automatisch.
A4: 🗂 EURE DATEN
A5: Wir heiraten (Namen) | B5: Anna & Tom
A6: Hochzeitsdatum | B6: 46550
A7: Hauptlocation | B7: Gut Thansen, Lüneburger Heide
A8: Gesamtbudget | B8: 25000
A10: 📊 AUF EINEN BLICK
A12: 📅 Tage bis zur Hochzeit | E12: =IF(B6="","",B6-TODAY()) -> 284
A14: 💶 Budget-Puffer | E14: =B8-SUM(BUDGET!D6:D65) -> 6001
A16: ✅ Aufgaben erledigt | E16: =IF(COUNTA(CHECKLISTE!E6:E70)=0,0,COUNTIF(CHECKLISTE!E6:E70,"Erledigt")/COUNTA(CHECKLISTE!E6:E70)) -> 0
A19: 💶 BUDGET IM DETAIL
A20: Gesamtbudget | B20: =B8 -> 25000
A21: Geplante Kosten | B21: =SUM(BUDGET!D6:D65) -> 18999
A22: Verbindliche Angebote | B22: =SUM(BUDGET!E6:E65) -> 16049
A23: Tatsächlich bezahlt | B23: =SUM(BUDGET!F6:F65) -> 3299
A24: Noch offen (Rest an Dienstleister) | B24: =SUM(BUDGET!H6:H65) -> 12750
A25: Puffer zum Budget | B25: =B20-B21 -> 6001
A28: ✅ AUFGABEN IM DETAIL
A29: Aufgaben gesamt | B29: =COUNTA(CHECKLISTE!E6:E70) -> 48
A30: Erledigt | B30: =COUNTIF(CHECKLISTE!E6:E70,"Erledigt") -> 0
A31: In Arbeit | B31: =COUNTIF(CHECKLISTE!E6:E70,"In Arbeit") -> 0
A32: Offen | B32: =COUNTIF(CHECKLISTE!E6:E70,"Offen") -> 48
A35: 👥 GÄSTE JE EVENT
A36: Die Namen kommen automatisch aus dem Blatt EVENTS.
A37: Event | B37: Zusagen | C37: Absagen | D37: Offen | E37: Eingeladen
A38: =EVENTS!B6 -> Standesamt | B38: =COUNTIF(GÄSTELISTE!K6:K305,"Zusage") -> 1 | C38: =COUNTIF(GÄSTELISTE!K6:K305,"Absage") -> 0 | D38: =COUNTIF(GÄSTELISTE!K6:K305,"Offen") -> 0 | E38: =COUNTIF(GÄSTELISTE!K6:K305,"Eingeladen") -> 2
A39: =EVENTS!B7 -> Welcome Dinner | B39: =COUNTIF(GÄSTELISTE!L6:L305,"Zusage") -> 1 | C39: =COUNTIF(GÄSTELISTE!L6:L305,"Absage") -> 2 | D39: =COUNTIF(GÄSTELISTE!L6:L305,"Offen") -> 0 | E39: =COUNTIF(GÄSTELISTE!L6:L305,"Eingeladen") -> 0
A40: =EVENTS!B8 -> Freie Trauung | B40: =COUNTIF(GÄSTELISTE!M6:M305,"Zusage") -> 3 | C40: =COUNTIF(GÄSTELISTE!M6:M305,"Absage") -> 0 | D40: =COUNTIF(GÄSTELISTE!M6:M305,"Offen") -> 0 | E40: =COUNTIF(GÄSTELISTE!M6:M305,"Eingeladen") -> 0
A41: =EVENTS!B9 -> Hochzeitsfeier | B41: =COUNTIF(GÄSTELISTE!N6:N305,"Zusage") -> 3 | C41: =COUNTIF(GÄSTELISTE!N6:N305,"Absage") -> 0 | D41: =COUNTIF(GÄSTELISTE!N6:N305,"Offen") -> 0 | E41: =COUNTIF(GÄSTELISTE!N6:N305,"Eingeladen") -> 0
A42: =EVENTS!B10 -> Brunch | B42: =COUNTIF(GÄSTELISTE!O6:O305,"Zusage") -> 1 | C42: =COUNTIF(GÄSTELISTE!O6:O305,"Absage") -> 2 | D42: =COUNTIF(GÄSTELISTE!O6:O305,"Offen") -> 0 | E42: =COUNTIF(GÄSTELISTE!O6:O305,"Eingeladen") -> 0
A44: Personen gesamt auf der Gästeliste | B44: =COUNTA(GÄSTELISTE!C6:C305) -> 3
A47: Hinweis: Die Beispielzeilen sind mit „BEISPIEL“ gekennzeichnet — einfach überschreiben oder löschen.

Sheet ANLEITUNG
A1: 📖 Anleitung & Tipps
B4: So funktioniert der Planer
B5: Gelb hinterlegte Felder sind eure Eingabefelder. Alles andere rechnet sich automatisch — bitte nicht überschreiben, sonst geht die Formel verloren.
B6: Fangt auf dem Blatt START an: Namen, Hochzeitsdatum und Gesamtbudget eintragen. Danach das Blatt EVENTS ausfüllen.
B7: Jede Zeile, die mit „BEISPIEL“ beginnt, ist nur zur Veranschaulichung da. Überschreibt sie mit euren echten Daten oder löscht sie.
B8: Die Reihenfolge, die sich bewährt hat
B9: 1. EVENTS — Welche Programmpunkte hat eure Hochzeit? Standesamt, Welcome Dinner, freie Trauung, Feier, Brunch am Folgetag. Auch wenn ihr nur einen Termin habt: Tragt ihn als Event 1 ein, denn die Gästeliste greift darauf zu.
B10: 2. GÄSTELISTE — Alle Personen erfassen. Für jedes Event gibt es eine eigene Zu-/Absage-Spalte. So könnt ihr abbilden, dass jemand zur Feier kommt, aber nicht zum Brunch.
B11: 3. BUDGET — Erst grob planen, dann die Angebote eintragen, zuletzt die tatsächlichen Zahlungen.
B12: 4. CHECKLISTE — Ist bereits mit den üblichen Aufgaben vorbefüllt. Streicht, was nicht passt, und ergänzt Eigenes.
B13: 5. DIENSTLEISTER, SITZPLAN und TAGESABLAUF füllt ihr, sobald die Zusagen da sind.
B14: Mehrtägige Hochzeiten
B15: Der Planer ist auf bis zu fünf Programmpunkte ausgelegt. Tragt jeden Tag oder jede Zeremonie als eigenes Event ein — die Gästeliste bekommt dadurch automatisch eine eigene Rückmeldespalte je Event.
... B30: Erstellt von Zwischen Heide & Herz — Freie Trauungen & Hochzeitswebsites

Sheet EVENTS
A1: 📅 Events
A2: Jeder Programmpunkt eurer Hochzeit. Die Namen in Spalte B steuern die Gästeliste und das Dashboard.
A5: Nr. | B5: Event-Name | C5: Datum | D5: von | E5: bis | F5: Ort | G5: Adresse | H5: Dresscode | I5: Ansprechpartner | J5: Notizen
A6: 1 | B6: Standesamt | C6: 46549 | D6: 11:00 | E6: 12:00 | F6: Standesamt Salzhausen | G6: Marktplatz 1, 21376 Salzhausen | H6: Elegant | I6: Standesbeamtin Frau Meier | J6: BEISPIEL — nur enge Familie
A7: 2 | B7: Welcome Dinner | C7: 46549 | D7: 19:00 | E7: 23:00 | F7: Landhaus Höpen | G7: Höpen 3, 29646 Bispingen | H7: Casual | I7: Restaurantleitung | J7: BEISPIEL — für angereiste Gäste
A8: 3 | B8: Freie Trauung | C8: 46550 | D8: 14:00 | E8: 15:00 | F8: Gut Thansen, Heidegarten | G8: Thansen 1, 21388 Soderstorf | H8: Sommerlich festlich | I8: Eduard Schmal | J8: BEISPIEL
A9: 4 | B9: Hochzeitsfeier | C9: 46550 | D9: 16:00 | E9: 03:00 | F9: Gut Thansen, Scheune | G9: Thansen 1, 21388 Soderstorf | H9: Sommerlich festlich | I9: Eventmanagerin | J9: BEISPIEL
A10: 5 | B10: Brunch | C10: 46551 | D10: 10:00 | E10: 14:00 | F10: Gut Thansen, Terrasse | G10: Thansen 1, 21388 Soderstorf | H10: Leger | I10: Eventmanagerin | J10: BEISPIEL — nur Übernachtungsgäste
A12: Nicht mehr als fünf Events — die Gästeliste ist auf fünf Rückmeldespalten ausgelegt.

Sheet GÄSTELISTE
A1: 👥 Gästeliste
A2: Eine Zeile je Person. Die Spalten K bis O sind die Rückmeldungen je Event.
A5: Nr. | B5: Vorname | C5: Nachname | D5: E-Mail | E5: Telefon | F5: Gruppe | G5: Alter | H5: Essenswunsch | I5: Allergien / Unverträglichkeiten | J5: Übernachtung | K5: =EVENTS!B6 -> Standesamt | L5: =EVENTS!B7 -> Welcome Dinner | M5: =EVENTS!B8 -> Freie Trauung | N5: =EVENTS!B9 -> Hochzeitsfeier | O5: =EVENTS!B10 -> Brunch | P5: Notizen | Q5: Suchname (automatisch)
A6: 1 | B6: Maria | C6: Schmidt | D6: maria.schmidt@example.de | E6: 0151 2345678 | F6: Familie Braut | G6: Erwachsen | H6: Vegetarisch | I6: Nussallergie | J6: Ja | K6: Zusage | L6: Zusage | M6: Zusage | N6: Zusage | O6: Zusage | P6: BEISPIEL — bitte überschreiben | Q6: =IF(B6="","",B6&" "&C6) -> Maria Schmidt
A7: 2 | B7: Jonas | C7: Weber | D7: jonas.weber@example.de | E7: 0170 9876543 | F7: Freunde | G7: Erwachsen | H7: Fleisch | J7: Nein | K7: Eingeladen | L7: Absage | M7: Zusage | N7: Zusage | O7: Absage | P7: BEISPIEL — kommt nicht zum Brunch | Q7: =IF(B7="","",B7&" "&C7) -> Jonas Weber
A8: 3 | B8: Lina | C8: Weber | F8: Freunde | G8: Kind | H8: Kindermenü | I8: Laktose | J8: Nein | K8: Eingeladen | L8: Absage | M8: Zusage | N8: Zusage | O8: Absage | P8: BEISPIEL | Q8: =IF(B8="","",B8&" "&C8) -> Lina Weber
Q9: =IF(B9="","",B9&" "&C9)
Q10: =IF(B10="","",B10&" "&C10)
Q11: =IF(B11="","",B11&" "&C11)
Q12: =IF(B12="","",B12&" "&C12)
Q13: =IF(B13="","",B13&" "&C13)
Q14: =IF(B14="","",B14&" "&C14)
Q15: =IF(B15="","",B15&" "&C15)
Q16: =IF(B16="","",B16&" "&C16)
Q17: =IF(B17="","",B17&" "&C17)
Q18: =IF(B18="","",B18&" "&C18)
Q19: =IF(B19="","",B19&" "&C19)
Q20: =IF(B20="","",B20&" "&C20)
... Q305: =IF(B305="","",B305&" "&C305)

Sheet BUDGET
A1: 💶 Budget
A2: Spalte H rechnet automatisch: was nach der Anzahlung noch offen ist.
A5: Kategorie | B5: Position | C5: Dienstleister | D5: Geplant | E5: Angebot | F5: Bezahlt | G5: Anzahlung | H5: Noch offen | I5: Status | J5: Fällig am | K5: Notizen
A6: Location | B6: Miete Scheune & Heidegarten | C6: Gut Thansen | D6: 6500 | E6: 6800 | F6: 2000 | G6: 2000 | H6: =IF(E6=0,0,E6-G6) -> 4800 | I6: Angezahlt | J6: 46402 | K6: BEISPIEL
A7: Catering | B7: Menü & Getränke, 75 Personen | C7: Landküche Nord | D7: 7500 | E7: 7950 | F7: 0 | G7: 0 | H7: =IF(E7=0,0,E7-G7) -> 7950 | I7: Angebot liegt vor | J7: 46519 | K7: BEISPIEL
A8: Zeremonie | B8: Freie Trauung | C8: Zwischen Heide & Herz | D8: 1299 | E8: 1299 | F8: 1299 | G8: 1299 | H8: =IF(E8=0,0,E8-G8) -> 0 | I8: Bezahlt | J8: 46356 | K8: BEISPIEL — Komfortpaket
A9: Foto & Video | B9: Fotograf ganztags | D9: 2200 | E9: 0 | F9: 0 | G9: 0 | H9: =IF(E9=0,0,E9-G9) -> 0 | I9: Offen | K9: BEISPIEL
A10: Dekoration | B10: Blumen & Tischdeko | D10: 1500 | E10: 0 | F10: 0 | G10: 0 | H10: =IF(E10=0,0,E10-G10) -> 0 | I10: Offen | K10: BEISPIEL — wird oft unterschätzt
H11: =IF(E11=0,0,E11-G11) -> 0
H12: =IF(E12=0,0,E12-G12) -> 0
H13: =IF(E13=0,0,E13-G13) -> 0
H14: =IF(E14=0,0,E14-G14) -> 0
H15: =IF(E15=0,0,E15-G15) -> 0
H16: =IF(E16=0,0,E16-G16) -> 0
H17: =IF(E17=0,0,E17-G17) -> 0
H18: =IF(E18=0,0,E18-G18) -> 0
H19: =IF(E19=0,0,E19-G19) -> 0
H20: =IF(E20=0,0,E20-G20) -> 0
H21: =IF(E21=0,0,E21-G21) -> 0
H22: =IF(E22=0,0,E22-G22) -> 0
... H65: =IF(E65=0,0,E65-G65) -> 0
C67: SUMME | D67: =SUM(D6:D65) -> 18999 | E67: =SUM(E6:E65) -> 16049 | F67: =SUM(F6:F65) -> 3299 | G67: =SUM(G6:G65) -> 3299 | H67: =SUM(H6:H65) -> 12750

Sheet CHECKLISTE
A1: ✅ Checkliste
A2: Vorbefüllt mit den üblichen Aufgaben. Streicht, was nicht passt, ergänzt Eigenes.
A5: Zeitfenster | B5: Aufgabe | C5: Zuständig | D5: Frist | E5: Status | F5: Notizen
A6: 12+ Monate vorher | B6: Budgetrahmen festlegen und Finanzierung klären | E6: Offen
A7: 12+ Monate vorher | B7: Wunschtermin und Alternativtermine festlegen | E7: Offen
A8: 12+ Monate vorher | B8: Grobe Gästezahl bestimmen | E8: Offen
A9: 12+ Monate vorher | B9: Location besichtigen und reservieren | E9: Offen
A10: 12+ Monate vorher | B10: Standesamt-Termin anfragen | E10: Offen
A11: 12+ Monate vorher | B11: Trauredner für die freie Trauung anfragen | E11: Offen
A12: 12+ Monate vorher | B12: Fotograf und Videograf anfragen | E12: Offen
A13: 9–12 Monate vorher | B13: Save-the-Date verschicken | E13: Offen
A14: 9–12 Monate vorher | B14: Catering auswählen und Probeessen vereinbaren | E14: Offen
A15: 9–12 Monate vorher | B15: Musik klären: Band oder DJ | E15: Offen
A16: 9–12 Monate vorher | B16: Brautkleid und Anzug aussuchen | E16: Offen
A17: 9–12 Monate vorher | B17: Trauzeugen fragen | E17: Offen
... A53: Nach der Hochzeit | B53: Namensänderung bei Ämtern und Banken | E53: Offen

Sheet DIENSTLEISTER
A1: 🤝 Dienstleister
A2: Vergleichen, buchen, den Überblick behalten.
A5: Kategorie | B5: Anbieter | C5: Ansprechpartner | D5: Telefon | E5: E-Mail | F5: Angebot | G5: Status | H5: Vertrag unterschrieben | I5: Bewertung 1–5 | J5: Notizen
A6: Location | B6: Gut Thansen | C6: Frau Ahrens | D6: 04172 123456 | E6: info@example.de | F6: 6800 | G6: Gebucht | H6: Ja | I6: 5 | J6: BEISPIEL
A7: Zeremonie | B7: Zwischen Heide & Herz | C7: Eduard Schmal | E7: hallo@example.de | F7: 1299 | G7: Gebucht | H7: Ja | I7: 5 | J7: BEISPIEL — Komfortpaket
A8: Foto & Video | B8: Studio Nordlicht | F8: 2200 | G8: Angebot liegt vor | H8: Nein | I8: 4 | J8: BEISPIEL

Sheet SITZPLAN
A1: 🪑 Sitzplan
A2: Spalte D prüft automatisch, ob die Person für die Feier zugesagt hat.
A5: Tisch | B5: Platz | C5: Vorname | D5: Nachname | E5: Zugesagt? | F5: Essenswunsch | G5: Notizen
A6: Tisch 1 — Brautpaar | B6: 1 | C6: Maria | D6: Schmidt | E6: =IF(C6="","",IFERROR(INDEX(GÄSTELISTE!N$6:N$305,MATCH(C6&" "&D6,GÄSTELISTE!Q$6:Q$305,0)),"nicht gefunden")) -> Zusage | F6: =IF(C6="","",IFERROR(INDEX(GÄSTELISTE!H$6:H$305,MATCH(C6&" "&D6,GÄSTELISTE!Q$6:Q$305,0)),"")) -> Vegetarisch
A7: Tisch 1 — Brautpaar | B7: 2 | C7: Jonas | D7: Weber | E7: =IF(C7="","",IFERROR(INDEX(GÄSTELISTE!N$6:N$305,MATCH(C7&" "&D7,GÄSTELISTE!Q$6:Q$305,0)),"nicht gefunden")) -> Zusage | F7: =IF(C7="","",IFERROR(INDEX(GÄSTELISTE!H$6:H$305,MATCH(C7&" "&D7,GÄSTELISTE!Q$6:Q$305,0)),"")) -> Fleisch
E8: =IF(C8="","",IFERROR(INDEX(GÄSTELISTE!N$6:N$305,MATCH(C8&" "&D8,GÄSTELISTE!Q$6:Q$305,0)),"nicht gefunden")) | F8: =IF(C8="","",IFERROR(INDEX(GÄSTELISTE!H$6:H$305,MATCH(C8&" "&D8,GÄSTELISTE!Q$6:Q$305,0)),""))
E9: =IF(C9="","",IFERROR(INDEX(GÄSTELISTE!N$6:N$305,MATCH(C9&" "&D9,GÄSTELISTE!Q$6:Q$305,0)),"nicht gefunden")) | F9: =IF(C9="","",IFERROR(INDEX(GÄSTELISTE!H$6:H$305,MATCH(C9&" "&D9,GÄSTELISTE!Q$6:Q$305,0)),""))
E10: =IF(C10="","",IFERROR(INDEX(GÄSTELISTE!N$6:N$305,MATCH(C10&" "&D10,GÄSTELISTE!Q$6:Q$305,0)),"nicht gefunden")) | F10: =IF(C10="","",IFERROR(INDEX(GÄSTELISTE!H$6:H$305,MATCH(C10&" "&D10,GÄSTELISTE!Q$6:Q$305,0)),""))
E11: =IF(C11="","",IFERROR(INDEX(GÄSTELISTE!N$6:N$305,MATCH(C11&" "&D11,GÄSTELISTE!Q$6:Q$305,0)),"nicht gefunden")) | F11: =IF(C11="","",IFERROR(INDEX(GÄSTELISTE!H$6:H$305,MATCH(C11&" "&D11,GÄSTELISTE!Q$6:Q$305,0)),""))
E12: =IF(C12="","",IFERROR(INDEX(GÄSTELISTE!N$6:N$305,MATCH(C12&" "&D12,GÄSTELISTE!Q$6:Q$305,0)),"nicht gefunden")) | F12: =IF(C12="","",IFERROR(INDEX(GÄSTELISTE!H$6:H$305,MATCH(C12&" "&D12,GÄSTELISTE!Q$6:Q$305,0)),""))
E13: =IF(C13="","",IFERROR(INDEX(GÄSTELISTE!N$6:N$305,MATCH(C13&" "&D13,GÄSTELISTE!Q$6:Q$305,0)),"nicht gefunden")) | F13: =IF(C13="","",IFERROR(INDEX(GÄSTELISTE!H$6:H$305,MATCH(C13&" "&D13,GÄSTELISTE!Q$6:Q$305,0)),""))
E14: =IF(C14="","",IFERROR(INDEX(GÄSTELISTE!N$6:N$305,MATCH(C14&" "&D14,GÄSTELISTE!Q$6:Q$305,0)),"nicht gefunden")) | F14: =IF(C14="","",IFERROR(INDEX(GÄSTELISTE!H$6:H$305,MATCH(C14&" "&D14,GÄSTELISTE!Q$6:Q$305,0)),""))
E15: =IF(C15="","",IFERROR(INDEX(GÄSTELISTE!N$6:N$305,MATCH(C15&" "&D15,GÄSTELISTE!Q$6:Q$305,0)),"nicht gefunden")) | F15: =IF(C15="","",IFERROR(INDEX(GÄSTELISTE!H$6:H$305,MATCH(C15&" "&D15,GÄSTELISTE!Q$6:Q$305,0)),""))
E16: =IF(C16="","",IFERROR(INDEX(GÄSTELISTE!N$6:N$305,MATCH(C16&" "&D16,GÄSTELISTE!Q$6:Q$305,0)),"nicht gefunden")) | F16: =IF(C16="","",IFERROR(INDEX(GÄSTELISTE!H$6:H$305,MATCH(C16&" "&D16,GÄSTELISTE!Q$6:Q$305,0)),""))
E17: =IF(C17="","",IFERROR(INDEX(GÄSTELISTE!N$6:N$305,MATCH(C17&" "&D17,GÄSTELISTE!Q$6:Q$305,0)),"nicht gefunden")) | F17: =IF(C17="","",IFERROR(INDEX(GÄSTELISTE!H$6:H$305,MATCH(C17&" "&D17,GÄSTELISTE!Q$6:Q$305,0)),""))
E18: =IF(C18="","",IFERROR(INDEX(GÄSTELISTE!N$6:N$305,MATCH(C18&" "&D18,GÄSTELISTE!Q$6:Q$305,0)),"nicht gefunden")) | F18: =IF(C18="","",IFERROR(INDEX(GÄSTELISTE!H$6:H$305,MATCH(C18&" "&D18,GÄSTELISTE!Q$6:Q$305,0)),""))
E19: =IF(C19="","",IFERROR(INDEX(GÄSTELISTE!N$6:N$305,MATCH(C19&" "&D19,GÄSTELISTE!Q$6:Q$305,0)),"nicht gefunden")) | F19: =IF(C19="","",IFERROR(INDEX(GÄSTELISTE!H$6:H$305,MATCH(C19&" "&D19,GÄSTELISTE!Q$6:Q$305,0)),""))
... E160: =IF(C160="","",IFERROR(INDEX(GÄSTELISTE!N$6:N$305,MATCH(C160&" "&D160,GÄSTELISTE!Q$6:Q$305,0)),"nicht gefunden")) | F160: =IF(C160="","",IFERROR(INDEX(GÄSTELISTE!H$6:H$305,MATCH(C160&" "&D160,GÄSTELISTE!Q$6:Q$305,0)),""))
A162: Spalte E und F holen sich die Daten aus der Gästeliste (Rückmeldung zum 4. Event). Schreibt Vor- und Nachname genau so wie dort.

Sheet TAGESABLAUF
A1: 🕐 Tagesablauf
A2: Das Dokument, das eure Dienstleister brauchen. Teilt es rechtzeitig.
A5: Event | B5: Uhrzeit | C5: Programmpunkt | D5: Dauer (Min.) | E5: Zuständig | F5: Ort | G5: Notizen
A6: Freie Trauung | B6: 13:30 | C6: Gäste treffen ein, Sektempfang | D6: 30 | E6: Location | F6: Heidegarten | G6: BEISPIEL
A7: Freie Trauung | B7: 14:00 | C7: Einzug und Zeremonie | D7: 60 | E7: Trauredner | F7: Heidegarten | G7: BEISPIEL
A8: Hochzeitsfeier | B8: 15:00 | C8: Gratulation und Gruppenfoto | D8: 45 | E8: Fotograf | F8: Vor der Scheune | G8: BEISPIEL
A9: Hochzeitsfeier | B9: 16:00 | C9: Kaffee und Kuchen | D9: 60 | E9: Catering | F9: Scheune | G9: BEISPIEL
A10: Hochzeitsfeier | B10: 18:30 | C10: Abendessen | D10: 90 | E10: Catering | F10: Scheune | G10: BEISPIEL
A11: Hochzeitsfeier | B11: 20:30 | C11: Eröffnungstanz | D11: 15 | E11: DJ | F11: Scheune | G11: BEISPIEL
